jsop.py
jsop-1.3.1.dist-info/LICENSE.txt
jsop-1.3.1.dist-info/METADATA
jsop-1.3.1.dist-info/WHEEL
jsop-1.3.1.dist-info/top_level.txt
jsop-1.3.1.dist-info/RECORD
