Metadata-Version: 2.1
Name: jsop
Version: 1.3.1
Summary: Store big JSON-style files, but access the data quickly.
Home-page: https://github.com/hagai-helman/jsop
Author: Hagai Helman Tov
Author-email: hagai.helman@gmail.com
License: MIT
Keywords: JSON,dbm,persistence
Platform: UNKNOWN
Classifier: Development Status :: 5 - Production/Stable
Classifier: License :: OSI Approved :: MIT License
Classifier: Intended Audience :: Developers
Classifier: Programming Language :: Python :: 3
Classifier: Programming Language :: Python :: 3.6
Requires-Python: ~=3.6
License-File: LICENSE.txt
